LICENSE.txt
MANIFEST.in
README.rst
setup.py
tsv.py
linear_tsv.egg-info/PKG-INFO
linear_tsv.egg-info/SOURCES.txt
linear_tsv.egg-info/dependency_links.txt
linear_tsv.egg-info/requires.txt
linear_tsv.egg-info/top_level.txt