Metadata-Version: 1.1
Name: linear-tsv
Version: 1.1.0
Summary: Line-oriented, tab-separated value format
Home-page: https://github.com/solidsnack/tsv
Author: Jason Dusek
Author-email: jason.dusek@gmail.com
License: Apache
Platform: UNKNOWN
Classifier: License :: OSI Approved :: Apache Software License
Classifier: Intended Audience :: Developers
Classifier: Programming Language :: Python
Classifier: Programming Language :: Python :: 2
Classifier: Programming Language :: Python :: 2.6
Classifier: Programming Language :: Python :: 2.7
Classifier: Programming Language :: Python :: 3
Classifier: Programming Language :: Python :: 3.5
Classifier: Development Status :: 4 - Beta
